Time/Time.py
Time/__init__.py
Library_Time-0.0.1.dist-info/METADATA
Library_Time-0.0.1.dist-info/WHEEL
Library_Time-0.0.1.dist-info/top_level.txt
Library_Time-0.0.1.dist-info/RECORD
